{"Buster Posey, C SF": "{\"PIT\":{\"Years\":1,\"Total\":0.78,\"Breakdown\":null,\"AAV\":0.78,\"Y1\":0.78,\"Y2\":0.78,\"Y3\":0.78,\"Y4\":0.78,\"Y5\":0.78,\"Max\":0.78,\"Min\":0.78,\"MaxValid\":true,\"MinValid\":true,\"BaseValid\":true,\"Valid\":true},\"LAD\":{\"Years\":2,\"Total\":1.6,\"Breakdown\":null,\"AAV\":0.8,\"Y1\":0.8,\"Y2\":0.8,\"Y3\":0.8,\"Y4\":0.8,\"Y5\":0.8,\"Max\":0.8,\"Min\":0.8,\"MaxValid\":true,\"MinValid\":true,\"BaseValid\":true,\"Valid\":true},\"BOS\":{\"Years\":2,\"Total\":5.78,\"Breakdown\":null,\"AAV\":2.89,\"Y1\":2.89,\"Y2\":2.89,\"Y3\":2.89,\"Y4\":2.89,\"Y5\":2.89,\"Max\":2.89,\"Min\":2.89,\"MaxValid\":true,\"MinValid\":true,\"BaseValid\":true,\"Valid\":true},\"ARZ\":{\"Years\":1,\"Total\":6.3,\"Breakdown\":null,\"AAV\":6.3,\"Y1\":6.3,\"Y2\":6.3,\"Y3\":6.3,\"Y4\":6.3,\"Y5\":6.3,\"Max\":6.3,\"Min\":6.3,\"MaxValid\":true,\"MinValid\":true,\"BaseValid\":true,\"Valid\":true},\"OAK\":{\"Years\":3,\"Total\":9.0,\"Breakdown\":null,\"AAV\":3.0,\"Y1\":3.0,\"Y2\":3.0,\"Y3\":3.0,\"Y4\":3.0,\"Y5\":3.0,\"Max\":3.0,\"Min\":3.0,\"MaxValid\":true,\"MinValid\":true,\"BaseValid\":true,\"Valid\":true},\"WAS\":{\"Years\":3,\"Total\":18.0,\"Breakdown\":null,\"AAV\":6.0,\"Y1\":6.0,\"Y2\":6.0,\"Y3\":6.0,\"Y4\":6.0,\"Y5\":6.0,\"Max\":6.0,\"Min\":6.0,\"MaxValid\":true,\"MinValid\":true,\"BaseValid\":true,\"Valid\":true},\"CHC\":{\"Years\":1,\"Total\":0.45,\"Breakdown\":null,\"AAV\":0.45,\"Y1\":0.45,\"Y2\":0.45,\"Y3\":0.45,\"Y4\":0.45,\"Y5\":0.45,\"Max\":0.45,\"Min\":0.45,\"MaxValid\":true,\"MinValid\":true,\"BaseValid\":true,\"Valid\":true},\"ATL\":{\"Years\":1,\"Total\":1.2,\"Breakdown\":null,\"AAV\":1.2,\"Y1\":1.2,\"Y2\":1.2,\"Y3\":1.2,\"Y4\":1.2,\"Y5\":1.2,\"Max\":1.2,\"Min\":1.2,\"MaxValid\":true,\"MinValid\":true,\"BaseValid\":true,\"Valid\":true},\"CLE\":{\"Years\":2,\"Total\":6.6,\"Breakdown\":null,\"AAV\":3.3,\"Y1\":3.3,\"Y2\":3.3,\"Y3\":3.3,\"Y4\":3.3,\"Y5\":3.3,\"Max\":3.3,\"Min\":3.3,\"MaxValid\":true,\"MinValid\":true,\"BaseValid\":true,\"Valid\":true},\"TOR\":{\"Years\":1,\"Total\":1.3,\"Breakdown\":null,\"AAV\":1.3,\"Y1\":1.3,\"Y2\":1.3,\"Y3\":1.3,\"Y4\":1.3,\"Y5\":1.3,\"Max\":1.3,\"Min\":1.3,\"MaxValid\":true,\"MinValid\":true,\"BaseValid\":true,\"Valid\":true}}", "Chris Ianetta, C COL ": "{\"PIT\":{\"Years\":1,\"Total\":0.41,\"Breakdown\":null,\"AAV\":0.41,\"Y1\":0.41,\"Y2\":0.41,\"Y3\":0.41,\"Y4\":0.41,\"Y5\":0.41,\"Max\":0.41,\"Min\":0.41,\"MaxValid\":true,\"MinValid\":true,\"BaseValid\":true,\"Valid\":true},\"CHC\":{\"Years\":1,\"Total\":0.4,\"Breakdown\":null,\"AAV\":0.4,\"Y1\":0.4,\"Y2\":0.4,\"Y3\":0.4,\"Y4\":0.4,\"Y5\":0.4,\"Max\":0.4,\"Min\":0.4,\"MaxValid\":true,\"MinValid\":true,\"BaseValid\":false,\"Valid\":false}}", "Russell Martin, C LAD": "{\"CHC\":{\"Years\":1,\"Total\":0.4,\"Breakdown\":null,\"AAV\":0.4,\"Y1\":0.4,\"Y2\":0.4,\"Y3\":0.4,\"Y4\":0.4,\"Y5\":0.4,\"Max\":0.4,\"Min\":0.4,\"MaxValid\":true,\"MinValid\":true,\"BaseValid\":false,\"Valid\":false}}", "David Freese, 1B LAD": "{\"PIT\":{\"Years\":1,\"Total\":0.78,\"Breakdown\":null,\"AAV\":0.78,\"Y1\":0.78,\"Y2\":0.78,\"Y3\":0.78,\"Y4\":0.78,\"Y5\":0.78,\"Max\":0.78,\"Min\":0.78,\"MaxValid\":true,\"MinValid\":true,\"BaseValid\":true,\"Valid\":true}}", "Eric Hosmer, 1B SD": "{\"LAD\":{\"Years\":1,\"Total\":3.3,\"Breakdown\":null,\"AAV\":3.3,\"Y1\":3.3,\"Y2\":3.3,\"Y3\":3.3,\"Y4\":3.3,\"Y5\":3.3,\"Max\":3.3,\"Min\":3.3,\"MaxValid\":true,\"MinValid\":true,\"BaseValid\":true,\"Valid\":true},\"BOS\":{\"Years\":2,\"Total\":6.38,\"Breakdown\":null,\"AAV\":3.19,\"Y1\":3.19,\"Y2\":3.19,\"Y3\":3.19,\"Y4\":3.19,\"Y5\":3.19,\"Max\":3.19,\"Min\":3.19,\"MaxValid\":true,\"MinValid\":true,\"BaseValid\":true,\"Valid\":true},\"ARZ\":{\"Years\":1,\"Total\":2.5,\"Breakdown\":null,\"AAV\":2.5,\"Y1\":2.5,\"Y2\":2.5,\"Y3\":2.5,\"Y4\":2.5,\"Y5\":2.5,\"Max\":2.5,\"Min\":2.5,\"MaxValid\":true,\"MinValid\":true,\"BaseValid\":true,\"Valid\":true},\"OAK\":{\"Years\":3,\"Total\":9.0,\"Breakdown\":null,\"AAV\":3.0,\"Y1\":3.0,\"Y2\":3.0,\"Y3\":3.0,\"Y4\":3.0,\"Y5\":3.0,\"Max\":3.0,\"Min\":3.0,\"MaxValid\":true,\"MinValid\":true,\"BaseValid\":true,\"Valid\":true},\"PIT\":{\"Years\":2,\"Total\":9.62,\"Breakdown\":\"5.77,3.85\",\"AAV\":4.81,\"Y1\":5.77,\"Y2\":4.81,\"Y3\":4.81,\"Y4\":4.81,\"Y5\":4.81,\"Max\":5.77,\"Min\":4.81,\"MaxValid\":true,\"MinValid\":true,\"BaseValid\":true,\"Valid\":true},\"WAS\":{\"Years\":1,\"Total\":4.0,\"Breakdown\":null,\"AAV\":4.0,\"Y1\":4.0,\"Y2\":4.0,\"Y3\":4.0,\"Y4\":4.0,\"Y5\":4.0,\"Max\":4.0,\"Min\":4.0,\"MaxValid\":true,\"MinValid\":true,\"BaseValid\":true,\"Valid\":true},\"ATL\":{\"Years\":1,\"Total\":0.9,\"Breakdown\":null,\"AAV\":0.9,\"Y1\":0.9,\"Y2\":0.9,\"Y3\":0.9,\"Y4\":0.9,\"Y5\":0.9,\"Max\":0.9,\"Min\":0.9,\"MaxValid\":true,\"MinValid\":true,\"BaseValid\":true,\"Valid\":true},\"CLE\":{\"Years\":2,\"Total\":5.4,\"Breakdown\":null,\"AAV\":2.7,\"Y1\":2.7,\"Y2\":2.7,\"Y3\":2.7,\"Y4\":2.7,\"Y5\":2.7,\"Max\":2.7,\"Min\":2.7,\"MaxValid\":true,\"MinValid\":true,\"BaseValid\":true,\"Valid\":true}}", "Eric Thames, 1B MIL": "{\"BOS\":{\"Years\":3,\"Total\":1.2,\"Breakdown\":null,\"AAV\":0.4,\"Y1\":0.4,\"Y2\":0.4,\"Y3\":0.4,\"Y4\":0.4,\"Y5\":0.4,\"Max\":0.4,\"Min\":0.4,\"MaxValid\":true,\"MinValid\":true,\"BaseValid\":false,\"Valid\":false}}", "Ian Desmond, 1B COL": "{\"OAK\":{\"Years\":1,\"Total\":2.0,\"Breakdown\":null,\"AAV\":2.0,\"Y1\":2.0,\"Y2\":2.0,\"Y3\":2.0,\"Y4\":2.0,\"Y5\":2.0,\"Max\":2.0,\"Min\":2.0,\"MaxValid\":true,\"MinValid\":true,\"BaseValid\":true,\"Valid\":true},\"PIT\":{\"Years\":1,\"Total\":2.28,\"Breakdown\":null,\"AAV\":2.28,\"Y1\":2.28,\"Y2\":2.28,\"Y3\":2.28,\"Y4\":2.28,\"Y5\":2.28,\"Max\":2.28,\"Min\":2.28,\"MaxValid\":true,\"MinValid\":true,\"BaseValid\":true,\"Valid\":true},\"PHI\":{\"Years\":1,\"Total\":1.3,\"Breakdown\":null,\"AAV\":1.3,\"Y1\":1.3,\"Y2\":1.3,\"Y3\":1.3,\"Y4\":1.3,\"Y5\":1.3,\"Max\":1.3,\"Min\":1.3,\"MaxValid\":true,\"MinValid\":true,\"BaseValid\":true,\"Valid\":true},\"TB\":{\"Years\":1,\"Total\":2.97,\"Breakdown\":null,\"AAV\":2.97,\"Y1\":2.97,\"Y2\":2.97,\"Y3\":2.97,\"Y4\":2.97,\"Y5\":2.97,\"Max\":2.97,\"Min\":2.97,\"MaxValid\":true,\"MinValid\":true,\"BaseValid\":true,\"Valid\":true},\"ATL\":{\"Years\":1,\"Total\":0.5,\"Breakdown\":null,\"AAV\":0.5,\"Y1\":0.5,\"Y2\":0.5,\"Y3\":0.5,\"Y4\":0.5,\"Y5\":0.5,\"Max\":0.5,\"Min\":0.5,\"MaxValid\":true,\"MinValid\":true,\"BaseValid\":true,\"Valid\":true},\"CLE\":{\"Years\":2,\"Total\":3.8,\"Breakdown\":null,\"AAV\":1.9,\"Y1\":1.9,\"Y2\":1.9,\"Y3\":1.9,\"Y4\":1.9,\"Y5\":1.9,\"Max\":1.9,\"Min\":1.9,\"MaxValid\":true,\"MinValid\":true,\"BaseValid\":true,\"Valid\":true},\"TOR\":{\"Years\":1,\"Total\":2.4,\"Breakdown\":null,\"AAV\":2.4,\"Y1\":2.4,\"Y2\":2.4,\"Y3\":2.4,\"Y4\":2.4,\"Y5\":2.4,\"Max\":2.4,\"Min\":2.4,\"MaxValid\":true,\"MinValid\":true,\"BaseValid\":true,\"Valid\":true}}", "Max Muncy, 1B LAD": "{\"LAD\":{\"Years\":1,\"Total\":7.4,\"Breakdown\":null,\"AAV\":7.4,\"Y1\":7.4,\"Y2\":7.4,\"Y3\":7.4,\"Y4\":7.4,\"Y5\":7.4,\"Max\":7.4,\"Min\":7.4,\"MaxValid\":true,\"MinValid\":true,\"BaseValid\":true,\"Valid\":true},\"BOS\":{\"Years\":2,\"Total\":4.58,\"Breakdown\":null,\"AAV\":2.29,\"Y1\":2.29,\"Y2\":2.29,\"Y3\":2.29,\"Y4\":2.29,\"Y5\":2.29,\"Max\":2.29,\"Min\":2.29,\"MaxValid\":true,\"MinValid\":true,\"BaseValid\":true,\"Valid\":true},\"ARZ\":{\"Years\":1,\"Total\":7.0,\"Breakdown\":null,\"AAV\":7.0,\"Y1\":7.0,\"Y2\":7.0,\"Y3\":7.0,\"Y4\":7.0,\"Y5\":7.0,\"Max\":7.0,\"Min\":7.0,\"MaxValid\":true,\"MinValid\":true,\"BaseValid\":true,\"Valid\":true},\"NYM\":{\"Years\":1,\"Total\":0.75,\"Breakdown\":null,\"AAV\":0.75,\"Y1\":0.75,\"Y2\":0.75,\"Y3\":0.75,\"Y4\":0.75,\"Y5\":0.75,\"Max\":0.75,\"Min\":0.75,\"MaxValid\":true,\"MinValid\":true,\"BaseValid\":true,\"Valid\":true},\"OAK\":{\"Years\":2,\"Total\":10.0,\"Breakdown\":null,\"AAV\":5.0,\"Y1\":5.0,\"Y2\":5.0,\"Y3\":5.0,\"Y4\":5.0,\"Y5\":5.0,\"Max\":5.0,\"Min\":5.0,\"MaxValid\":true,\"MinValid\":true,\"BaseValid\":true,\"Valid\":true},\"WAS\":{\"Years\":2,\"Total\":10.0,\"Breakdown\":null,\"AAV\":5.0,\"Y1\":5.0,\"Y2\":5.0,\"Y3\":5.0,\"Y4\":5.0,\"Y5\":5.0,\"Max\":5.0,\"Min\":5.0,\"MaxValid\":true,\"MinValid\":true,\"BaseValid\":true,\"Valid\":true},\"SD\":{\"Years\":3,\"Total\":4.77,\"Breakdown\":null,\"AAV\":1.59,\"Y1\":1.59,\"Y2\":1.59,\"Y3\":1.59,\"Y4\":1.59,\"Y5\":1.59,\"Max\":1.59,\"Min\":1.59,\"MaxValid\":true,\"MinValid\":true,\"BaseValid\":true,\"Valid\":true},\"TB\":{\"Years\":2,\"Total\":12.8,\"Breakdown\":null,\"AAV\":6.4,\"Y1\":6.4,\"Y2\":6.4,\"Y3\":6.4,\"Y4\":6.4,\"Y5\":6.4,\"Max\":6.4,\"Min\":6.4,\"MaxValid\":true,\"MinValid\":true,\"BaseValid\":true,\"Valid\":true},\"PIT\":{\"Years\":3,\"Total\":24.84,\"Breakdown\":null,\"AAV\":8.28,\"Y1\":8.28,\"Y2\":8.28,\"Y3\":8.28,\"Y4\":8.28,\"Y5\":8.28,\"Max\":8.28,\"Min\":8.28,\"MaxValid\":true,\"MinValid\":true,\"BaseValid\":true,\"Valid\":true},\"CLE\":{\"Years\":2,\"Total\":3.6,\"Breakdown\":null,\"AAV\":1.8,\"Y1\":1.8,\"Y2\":1.8,\"Y3\":1.8,\"Y4\":1.8,\"Y5\":1.8,\"Max\":1.8,\"Min\":1.8,\"MaxValid\":true,\"MinValid\":true,\"BaseValid\":true,\"Valid\":true},\"TOR\":{\"Years\":2,\"Total\":11.6,\"Breakdown\":null,\"AAV\":5.8,\"Y1\":5.8,\"Y2\":5.8,\"Y3\":5.8,\"Y4\":5.8,\"Y5\":5.8,\"Max\":5.8,\"Min\":5.8,\"MaxValid\":true,\"MinValid\":true,\"BaseValid\":true,\"Valid\":true}}", "Enrique Hernandez, 2B LAD": "{\"LAD\":{\"Years\":1,\"Total\":0.6,\"Breakdown\":null,\"AAV\":0.6,\"Y1\":0.6,\"Y2\":0.6,\"Y3\":0.6,\"Y4\":0.6,\"Y5\":0.6,\"Max\":0.6,\"Min\":0.6,\"MaxValid\":true,\"MinValid\":true,\"BaseValid\":true,\"Valid\":true}}", "Ian Kinsler, 2B SD": "{\"TOR\":{\"Years\":1,\"Total\":0.5,\"Breakdown\":null,\"AAV\":0.5,\"Y1\":0.5,\"Y2\":0.5,\"Y3\":0.5,\"Y4\":0.5,\"Y5\":0.5,\"Max\":0.5,\"Min\":0.5,\"MaxValid\":true,\"MinValid\":true,\"BaseValid\":true,\"Valid\":true}}", "Wilmer Flores, 2B ARZ": "{\"LAD\":{\"Years\":3,\"Total\":4.2,\"Breakdown\":null,\"AAV\":1.4,\"Y1\":1.4,\"Y2\":1.4,\"Y3\":1.4,\"Y4\":1.4,\"Y5\":1.4,\"Max\":1.4,\"Min\":1.4,\"MaxValid\":true,\"MinValid\":true,\"BaseValid\":true,\"Valid\":true},\"BOS\":{\"Years\":2,\"Total\":2.98,\"Breakdown\":null,\"AAV\":1.49,\"Y1\":1.49,\"Y2\":1.49,\"Y3\":1.49,\"Y4\":1.49,\"Y5\":1.49,\"Max\":1.49,\"Min\":1.49,\"MaxValid\":true,\"MinValid\":true,\"BaseValid\":true,\"Valid\":true},\"NYM\":{\"Years\":3,\"Total\":1.53,\"Breakdown\":null,\"AAV\":0.51,\"Y1\":0.51,\"Y2\":0.51,\"Y3\":0.51,\"Y4\":0.51,\"Y5\":0.51,\"Max\":0.51,\"Min\":0.51,\"MaxValid\":true,\"MinValid\":true,\"BaseValid\":true,\"Valid\":true}}", "Chris Taylor, 3B LAD": "{\"LAD\":{\"Years\":1,\"Total\":4.3,\"Breakdown\":null,\"AAV\":4.3,\"Y1\":4.3,\"Y2\":4.3,\"Y3\":4.3,\"Y4\":4.3,\"Y5\":4.3,\"Max\":4.3,\"Min\":4.3,\"MaxValid\":true,\"MinValid\":true,\"BaseValid\":true,\"Valid\":true},\"ARZ\":{\"Years\":2,\"Total\":7.0,\"Breakdown\":null,\"AAV\":3.5,\"Y1\":3.5,\"Y2\":3.5,\"Y3\":3.5,\"Y4\":3.5,\"Y5\":3.5,\"Max\":3.5,\"Min\":3.5,\"MaxValid\":true,\"MinValid\":true,\"BaseValid\":true,\"Valid\":true},\"BOS\":{\"Years\":2,\"Total\":2.38,\"Breakdown\":null,\"AAV\":1.19,\"Y1\":1.19,\"Y2\":1.19,\"Y3\":1.19,\"Y4\":1.19,\"Y5\":1.19,\"Max\":1.19,\"Min\":1.19,\"MaxValid\":true,\"MinValid\":true,\"BaseValid\":true,\"Valid\":true},\"TB\":{\"Years\":2,\"Total\":5.58,\"Breakdown\":null,\"AAV\":2.79,\"Y1\":2.79,\"Y2\":2.79,\"Y3\":2.79,\"Y4\":2.79,\"Y5\":2.79,\"Max\":2.79,\"Min\":2.79,\"MaxValid\":true,\"MinValid\":true,\"BaseValid\":true,\"Valid\":true},\"ATL\":{\"Years\":1,\"Total\":0.7,\"Breakdown\":null,\"AAV\":0.7,\"Y1\":0.7,\"Y2\":0.7,\"Y3\":0.7,\"Y4\":0.7,\"Y5\":0.7,\"Max\":0.7,\"Min\":0.7,\"MaxValid\":true,\"MinValid\":true,\"BaseValid\":true,\"Valid\":true},\"CLE\":{\"Years\":2,\"Total\":1.5,\"Breakdown\":null,\"AAV\":0.75,\"Y1\":0.75,\"Y2\":0.75,\"Y3\":0.75,\"Y4\":0.75,\"Y5\":0.75,\"Max\":0.75,\"Min\":0.75,\"MaxValid\":true,\"MinValid\":true,\"BaseValid\":true,\"Valid\":true},\"TOR\":{\"Years\":1,\"Total\":1.3,\"Breakdown\":null,\"AAV\":1.3,\"Y1\":1.3,\"Y2\":1.3,\"Y3\":1.3,\"Y4\":1.3,\"Y5\":1.3,\"Max\":1.3,\"Min\":1.3,\"MaxValid\":true,\"MinValid\":true,\"BaseValid\":true,\"Valid\":true}}", "Eduardo Escobar, 3B ARZ": "{\"LAD\":{\"Years\":1,\"Total\":3.8,\"Breakdown\":null,\"AAV\":3.8,\"Y1\":3.8,\"Y2\":3.8,\"Y3\":3.8,\"Y4\":3.8,\"Y5\":3.8,\"Max\":3.8,\"Min\":3.8,\"MaxValid\":true,\"MinValid\":true,\"BaseValid\":true,\"Valid\":true},\"BOS\":{\"Years\":1,\"Total\":2.19,\"Breakdown\":null,\"AAV\":2.19,\"Y1\":2.19,\"Y2\":2.19,\"Y3\":2.19,\"Y4\":2.19,\"Y5\":2.19,\"Max\":2.19,\"Min\":2.19,\"MaxValid\":true,\"MinValid\":true,\"BaseValid\":true,\"Valid\":true},\"ARZ\":{\"Years\":1,\"Total\":2.0,\"Breakdown\":null,\"AAV\":2.0,\"Y1\":2.0,\"Y2\":2.0,\"Y3\":2.0,\"Y4\":2.0,\"Y5\":2.0,\"Max\":2.0,\"Min\":2.0,\"MaxValid\":true,\"MinValid\":true,\"BaseValid\":true,\"Valid\":true},\"NYM\":{\"Years\":3,\"Total\":1.5,\"Breakdown\":null,\"AAV\":0.5,\"Y1\":0.5,\"Y2\":0.5,\"Y3\":0.5,\"Y4\":0.5,\"Y5\":0.5,\"Max\":0.5,\"Min\":0.5,\"MaxValid\":true,\"MinValid\":true,\"BaseValid\":true,\"Valid\":true},\"WAS\":{\"Years\":1,\"Total\":2.0,\"Breakdown\":null,\"AAV\":2.0,\"Y1\":2.0,\"Y2\":2.0,\"Y3\":2.0,\"Y4\":2.0,\"Y5\":2.0,\"Max\":2.0,\"Min\":2.0,\"MaxValid\":true,\"MinValid\":true,\"BaseValid\":true,\"Valid\":true},\"SD\":{\"Years\":1,\"Total\":1.97,\"Breakdown\":null,\"AAV\":1.97,\"Y1\":1.97,\"Y2\":1.97,\"Y3\":1.97,\"Y4\":1.97,\"Y5\":1.97,\"Max\":1.97,\"Min\":1.97,\"MaxValid\":true,\"MinValid\":true,\"BaseValid\":true,\"Valid\":true},\"TB\":{\"Years\":2,\"Total\":10.68,\"Breakdown\":null,\"AAV\":5.34,\"Y1\":5.34,\"Y2\":5.34,\"Y3\":5.34,\"Y4\":5.34,\"Y5\":5.34,\"Max\":5.34,\"Min\":5.34,\"MaxValid\":true,\"MinValid\":true,\"BaseValid\":true,\"Valid\":true},\"BAL\":{\"Years\":1,\"Total\":3.5,\"Breakdown\":null,\"AAV\":3.5,\"Y1\":3.5,\"Y2\":3.5,\"Y3\":3.5,\"Y4\":3.5,\"Y5\":3.5,\"Max\":3.5,\"Min\":3.5,\"MaxValid\":true,\"MinValid\":true,\"BaseValid\":true,\"Valid\":true},\"CLE\":{\"Years\":2,\"Total\":1.2,\"Breakdown\":null,\"AAV\":0.6,\"Y1\":0.6,\"Y2\":0.6,\"Y3\":0.6,\"Y4\":0.6,\"Y5\":0.6,\"Max\":0.6,\"Min\":0.6,\"MaxValid\":true,\"MinValid\":true,\"BaseValid\":true,\"Valid\":true},\"TOR\":{\"Years\":1,\"Total\":4.2,\"Breakdown\":null,\"AAV\":4.2,\"Y1\":4.2,\"Y2\":4.2,\"Y3\":4.2,\"Y4\":4.2,\"Y5\":4.2,\"Max\":4.2,\"Min\":4.2,\"MaxValid\":true,\"MinValid\":true,\"BaseValid\":true,\"Valid\":true}}", "Justin Turner, 3B LAD": "{\"BOS\":{\"Years\":1,\"Total\":2.19,\"Breakdown\":null,\"AAV\":2.19,\"Y1\":2.19,\"Y2\":2.19,\"Y3\":2.19,\"Y4\":2.19,\"Y5\":2.19,\"Max\":2.19,\"Min\":2.19,\"MaxValid\":true,\"MinValid\":true,\"BaseValid\":true,\"Valid\":true},\"DET\":{\"Years\":4,\"Total\":36.0,\"Breakdown\":\"7.5,9,10,9.5\",\"AAV\":9.0,\"Y1\":7.5,\"Y2\":9.0,\"Y3\":9.0,\"Y4\":9.0,\"Y5\":9.0,\"Max\":9.0,\"Min\":7.5,\"MaxValid\":true,\"MinValid\":true,\"BaseValid\":true,\"Valid\":true},\"ARZ\":{\"Years\":1,\"Total\":10.1,\"Breakdown\":null,\"AAV\":10.1,\"Y1\":10.1,\"Y2\":10.1,\"Y3\":10.1,\"Y4\":10.1,\"Y5\":10.1,\"Max\":10.1,\"Min\":10.1,\"MaxValid\":true,\"MinValid\":true,\"BaseValid\":true,\"Valid\":true},\"NYM\":{\"Years\":1,\"Total\":3.5,\"Breakdown\":null,\"AAV\":3.5,\"Y1\":3.5,\"Y2\":3.5,\"Y3\":3.5,\"Y4\":3.5,\"Y5\":3.5,\"Max\":3.5,\"Min\":3.5,\"MaxValid\":true,\"MinValid\":true,\"BaseValid\":true,\"Valid\":true},\"OAK\":{\"Years\":1,\"Total\":3.0,\"Breakdown\":null,\"AAV\":3.0,\"Y1\":3.0,\"Y2\":3.0,\"Y3\":3.0,\"Y4\":3.0,\"Y5\":3.0,\"Max\":3.0,\"Min\":3.0,\"MaxValid\":true,\"MinValid\":true,\"BaseValid\":true,\"Valid\":true},\"WAS\":{\"Years\":2,\"Total\":10.0,\"Breakdown\":null,\"AAV\":5.0,\"Y1\":5.0,\"Y2\":5.0,\"Y3\":5.0,\"Y4\":5.0,\"Y5\":5.0,\"Max\":5.0,\"Min\":5.0,\"MaxValid\":true,\"MinValid\":true,\"BaseValid\":true,\"Valid\":true},\"SD\":{\"Years\":1,\"Total\":4.77,\"Breakdown\":null,\"AAV\":4.77,\"Y1\":4.77,\"Y2\":4.77,\"Y3\":4.77,\"Y4\":4.77,\"Y5\":4.77,\"Max\":4.77,\"Min\":4.77,\"MaxValid\":true,\"MinValid\":true,\"BaseValid\":true,\"Valid\":true},\"TB\":{\"Years\":1,\"Total\":7.41,\"Breakdown\":null,\"AAV\":7.41,\"Y1\":7.41,\"Y2\":7.41,\"Y3\":7.41,\"Y4\":7.41,\"Y5\":7.41,\"Max\":7.41,\"Min\":7.41,\"MaxValid\":true,\"MinValid\":true,\"BaseValid\":true,\"Valid\":true},\"BAL\":{\"Years\":1,\"Total\":9.0,\"Breakdown\":null,\"AAV\":9.0,\"Y1\":9.0,\"Y2\":9.0,\"Y3\":9.0,\"Y4\":9.0,\"Y5\":9.0,\"Max\":9.0,\"Min\":9.0,\"MaxValid\":true,\"MinValid\":true,\"BaseValid\":true,\"Valid\":true},\"CLE\":{\"Years\":2,\"Total\":7.8,\"Breakdown\":null,\"AAV\":3.9,\"Y1\":3.9,\"Y2\":3.9,\"Y3\":3.9,\"Y4\":3.9,\"Y5\":3.9,\"Max\":3.9,\"Min\":3.9,\"MaxValid\":true,\"MinValid\":true,\"BaseValid\":true,\"Valid\":true},\"TOR\":{\"Years\":1,\"Total\":6.2,\"Breakdown\":null,\"AAV\":6.2,\"Y1\":6.2,\"Y2\":6.2,\"Y3\":6.2,\"Y4\":6.2,\"Y5\":6.2,\"Max\":6.2,\"Min\":6.2,\"MaxValid\":true,\"MinValid\":true,\"BaseValid\":true,\"Valid\":true}}", "Nick Ahmed, SS ARZ": "{\"BOS\":{\"Years\":1,\"Total\":2.19,\"Breakdown\":null,\"AAV\":2.19,\"Y1\":2.19,\"Y2\":2.19,\"Y3\":2.19,\"Y4\":2.19,\"Y5\":2.19,\"Max\":2.19,\"Min\":2.19,\"MaxValid\":true,\"MinValid\":true,\"BaseValid\":true,\"Valid\":true},\"WAS\":{\"Years\":1,\"Total\":3.0,\"Breakdown\":null,\"AAV\":3.0,\"Y1\":3.0,\"Y2\":3.0,\"Y3\":3.0,\"Y4\":3.0,\"Y5\":3.0,\"Max\":3.0,\"Min\":3.0,\"MaxValid\":true,\"MinValid\":true,\"BaseValid\":true,\"Valid\":true}}", "Mac Williamson, OF SF": "{\"BOS\":{\"Years\":3,\"Total\":5.97,\"Breakdown\":\"2.3,2,1.67\",\"AAV\":1.99,\"Y1\":2.3,\"Y2\":1.99,\"Y3\":1.99,\"Y4\":1.99,\"Y5\":1.99,\"Max\":2.3,\"Min\":1.99,\"MaxValid\":true,\"MinValid\":true,\"BaseValid\":true,\"Valid\":true}}", "Andrew Suarez, SP SF": "{\"BOS\":{\"Years\":2,\"Total\":0.8,\"Breakdown\":null,\"AAV\":0.4,\"Y1\":0.4,\"Y2\":0.4,\"Y3\":0.4,\"Y4\":0.4,\"Y5\":0.4,\"Max\":0.4,\"Min\":0.4,\"MaxValid\":true,\"MinValid\":true,\"BaseValid\":false,\"Valid\":false},\"CHC\":{\"Years\":1,\"Total\":0.4,\"Breakdown\":null,\"AAV\":0.4,\"Y1\":0.4,\"Y2\":0.4,\"Y3\":0.4,\"Y4\":0.4,\"Y5\":0.4,\"Max\":0.4,\"Min\":0.4,\"MaxValid\":true,\"MinValid\":true,\"BaseValid\":false,\"Valid\":false},\"TB\":{\"Years\":4,\"Total\":3.4,\"Breakdown\":null,\"AAV\":0.85,\"Y1\":0.85,\"Y2\":0.85,\"Y3\":0.85,\"Y4\":0.85,\"Y5\":0.85,\"Max\":0.85,\"Min\":0.85,\"MaxValid\":true,\"MinValid\":true,\"BaseValid\":true,\"Valid\":true},\"TOR\":{\"Years\":4,\"Total\":2.8,\"Breakdown\":null,\"AAV\":0.7,\"Y1\":0.7,\"Y2\":0.7,\"Y3\":0.7,\"Y4\":0.7,\"Y5\":0.7,\"Max\":0.7,\"Min\":0.7,\"MaxValid\":true,\"MinValid\":true,\"BaseValid\":true,\"Valid\":true}}", "Derek Holland, SP SF": "{\"NYM\":{\"Years\":2,\"Total\":9.0,\"Breakdown\":\"3.6,5.4\",\"AAV\":4.5,\"Y1\":3.6,\"Y2\":4.5,\"Y3\":4.5,\"Y4\":4.5,\"Y5\":4.5,\"Max\":4.5,\"Min\":3.6,\"MaxValid\":true,\"MinValid\":false,\"BaseValid\":true,\"Valid\":false},\"KC\":{\"Years\":1,\"Total\":2.55,\"Breakdown\":null,\"AAV\":2.55,\"Y1\":2.55,\"Y2\":2.55,\"Y3\":2.55,\"Y4\":2.55,\"Y5\":2.55,\"Max\":2.55,\"Min\":2.55,\"MaxValid\":true,\"MinValid\":true,\"BaseValid\":true,\"Valid\":true},\"CHC\":{\"Years\":1,\"Total\":0.4,\"Breakdown\":null,\"AAV\":0.4,\"Y1\":0.4,\"Y2\":0.4,\"Y3\":0.4,\"Y4\":0.4,\"Y5\":0.4,\"Max\":0.4,\"Min\":0.4,\"MaxValid\":true,\"MinValid\":true,\"BaseValid\":false,\"Valid\":false},\"TB\":{\"Years\":1,\"Total\":2.35,\"Breakdown\":null,\"AAV\":2.35,\"Y1\":2.35,\"Y2\":2.35,\"Y3\":2.35,\"Y4\":2.35,\"Y5\":2.35,\"Max\":2.35,\"Min\":2.35,\"MaxValid\":true,\"MinValid\":true,\"BaseValid\":true,\"Valid\":true},\"ATL\":{\"Years\":1,\"Total\":0.8,\"Breakdown\":null,\"AAV\":0.8,\"Y1\":0.8,\"Y2\":0.8,\"Y3\":0.8,\"Y4\":0.8,\"Y5\":0.8,\"Max\":0.8,\"Min\":0.8,\"MaxValid\":true,\"MinValid\":true,\"BaseValid\":true,\"Valid\":true},\"TOR\":{\"Years\":1,\"Total\":0.9,\"Breakdown\":null,\"AAV\":0.9,\"Y1\":0.9,\"Y2\":0.9,\"Y3\":0.9,\"Y4\":0.9,\"Y5\":0.9,\"Max\":0.9,\"Min\":0.9,\"MaxValid\":true,\"MinValid\":true,\"BaseValid\":true,\"Valid\":true}}", "Drew Pomeranz, SP SF": "{\"LAD\":{\"Years\":2,\"Total\":1.6,\"Breakdown\":null,\"AAV\":0.8,\"Y1\":0.8,\"Y2\":0.8,\"Y3\":0.8,\"Y4\":0.8,\"Y5\":0.8,\"Max\":0.8,\"Min\":0.8,\"MaxValid\":true,\"MinValid\":true,\"BaseValid\":true,\"Valid\":true},\"BOS\":{\"Years\":2,\"Total\":2.58,\"Breakdown\":null,\"AAV\":1.29,\"Y1\":1.29,\"Y2\":1.29,\"Y3\":1.29,\"Y4\":1.29,\"Y5\":1.29,\"Max\":1.29,\"Min\":1.29,\"MaxValid\":true,\"MinValid\":true,\"BaseValid\":true,\"Valid\":true},\"DET\":{\"Years\":1,\"Total\":0.75,\"Breakdown\":null,\"AAV\":0.75,\"Y1\":0.75,\"Y2\":0.75,\"Y3\":0.75,\"Y4\":0.75,\"Y5\":0.75,\"Max\":0.75,\"Min\":0.75,\"MaxValid\":true,\"MinValid\":true,\"BaseValid\":true,\"Valid\":true},\"CHC\":{\"Years\":1,\"Total\":0.4,\"Breakdown\":null,\"AAV\":0.4,\"Y1\":0.4,\"Y2\":0.4,\"Y3\":0.4,\"Y4\":0.4,\"Y5\":0.4,\"Max\":0.4,\"Min\":0.4,\"MaxValid\":true,\"MinValid\":true,\"BaseValid\":false,\"Valid\":false},\"TB\":{\"Years\":2,\"Total\":3.5,\"Breakdown\":null,\"AAV\":1.75,\"Y1\":1.75,\"Y2\":1.75,\"Y3\":1.75,\"Y4\":1.75,\"Y5\":1.75,\"Max\":1.75,\"Min\":1.75,\"MaxValid\":true,\"MinValid\":true,\"BaseValid\":true,\"Valid\":true},\"ATL\":{\"Years\":1,\"Total\":0.4,\"Breakdown\":null,\"AAV\":0.4,\"Y1\":0.4,\"Y2\":0.4,\"Y3\":0.4,\"Y4\":0.4,\"Y5\":0.4,\"Max\":0.4,\"Min\":0.4,\"MaxValid\":true,\"MinValid\":true,\"BaseValid\":false,\"Valid\":false}}", "Jeff Samardzija, SP SF": "{\"DET\":{\"Years\":2,\"Total\":6.0,\"Breakdown\":null,\"AAV\":3.0,\"Y1\":3.0,\"Y2\":3.0,\"Y3\":3.0,\"Y4\":3.0,\"Y5\":3.0,\"Max\":3.0,\"Min\":3.0,\"MaxValid\":true,\"MinValid\":true,\"BaseValid\":true,\"Valid\":true},\"NYM\":{\"Years\":1,\"Total\":2.5,\"Breakdown\":null,\"AAV\":2.5,\"Y1\":2.5,\"Y2\":2.5,\"Y3\":2.5,\"Y4\":2.5,\"Y5\":2.5,\"Max\":2.5,\"Min\":2.5,\"MaxValid\":true,\"MinValid\":true,\"BaseValid\":true,\"Valid\":true},\"PHI\":{\"Years\":2,\"Total\":10.4,\"Breakdown\":null,\"AAV\":5.2,\"Y1\":5.2,\"Y2\":5.2,\"Y3\":5.2,\"Y4\":5.2,\"Y5\":5.2,\"Max\":5.2,\"Min\":5.2,\"MaxValid\":true,\"MinValid\":true,\"BaseValid\":true,\"Valid\":true},\"SD\":{\"Years\":1,\"Total\":1.77,\"Breakdown\":null,\"AAV\":1.77,\"Y1\":1.77,\"Y2\":1.77,\"Y3\":1.77,\"Y4\":1.77,\"Y5\":1.77,\"Max\":1.77,\"Min\":1.77,\"MaxValid\":true,\"MinValid\":true,\"BaseValid\":true,\"Valid\":true},\"ATL\":{\"Years\":1,\"Total\":0.5,\"Breakdown\":null,\"AAV\":0.5,\"Y1\":0.5,\"Y2\":0.5,\"Y3\":0.5,\"Y4\":0.5,\"Y5\":0.5,\"Max\":0.5,\"Min\":0.5,\"MaxValid\":true,\"MinValid\":true,\"BaseValid\":true,\"Valid\":true},\"CLE\":{\"Years\":3,\"Total\":2.7,\"Breakdown\":null,\"AAV\":0.9,\"Y1\":0.9,\"Y2\":0.9,\"Y3\":0.9,\"Y4\":0.9,\"Y5\":0.9,\"Max\":0.9,\"Min\":0.9,\"MaxValid\":true,\"MinValid\":true,\"BaseValid\":true,\"Valid\":true},\"TOR\":{\"Years\":1,\"Total\":0.6,\"Breakdown\":null,\"AAV\":0.6,\"Y1\":0.6,\"Y2\":0.6,\"Y3\":0.6,\"Y4\":0.6,\"Y5\":0.6,\"Max\":0.6,\"Min\":0.6,\"MaxValid\":true,\"MinValid\":true,\"BaseValid\":true,\"Valid\":true}}", "Johnny Cueto, SP SF": "{\"LAD\":{\"Years\":4,\"Total\":3.2,\"Breakdown\":null,\"AAV\":0.8,\"Y1\":0.8,\"Y2\":0.8,\"Y3\":0.8,\"Y4\":0.8,\"Y5\":0.8,\"Max\":0.8,\"Min\":0.8,\"MaxValid\":true,\"MinValid\":true,\"BaseValid\":true,\"Valid\":true},\"BOS\":{\"Years\":2,\"Total\":3.58,\"Breakdown\":null,\"AAV\":1.79,\"Y1\":1.79,\"Y2\":1.79,\"Y3\":1.79,\"Y4\":1.79,\"Y5\":1.79,\"Max\":1.79,\"Min\":1.79,\"MaxValid\":true,\"MinValid\":true,\"BaseValid\":true,\"Valid\":true},\"CHC\":{\"Years\":1,\"Total\":1.2,\"Breakdown\":null,\"AAV\":1.2,\"Y1\":1.2,\"Y2\":1.2,\"Y3\":1.2,\"Y4\":1.2,\"Y5\":1.2,\"Max\":1.2,\"Min\":1.2,\"MaxValid\":true,\"MinValid\":true,\"BaseValid\":true,\"Valid\":true},\"TB\":{\"Years\":3,\"Total\":3.0,\"Breakdown\":null,\"AAV\":1.0,\"Y1\":1.0,\"Y2\":1.0,\"Y3\":1.0,\"Y4\":1.0,\"Y5\":1.0,\"Max\":1.0,\"Min\":1.0,\"MaxValid\":true,\"MinValid\":true,\"BaseValid\":true,\"Valid\":true}}", "Kenta Maeda, SP LAD": "{\"LAD\":{\"Years\":2,\"Total\":5.4,\"Breakdown\":null,\"AAV\":2.7,\"Y1\":2.7,\"Y2\":2.7,\"Y3\":2.7,\"Y4\":2.7,\"Y5\":2.7,\"Max\":2.7,\"Min\":2.7,\"MaxValid\":true,\"MinValid\":true,\"BaseValid\":true,\"Valid\":true},\"BOS\":{\"Years\":3,\"Total\":14.37,\"Breakdown\":\"4.3,4.8,5.27\",\"AAV\":4.79,\"Y1\":4.3,\"Y2\":4.79,\"Y3\":4.79,\"Y4\":4.79,\"Y5\":4.79,\"Max\":4.79,\"Min\":4.3,\"MaxValid\":true,\"MinValid\":true,\"BaseValid\":true,\"Valid\":true},\"DET\":{\"Years\":1,\"Total\":0.75,\"Breakdown\":null,\"AAV\":0.75,\"Y1\":0.75,\"Y2\":0.75,\"Y3\":0.75,\"Y4\":0.75,\"Y5\":0.75,\"Max\":0.75,\"Min\":0.75,\"MaxValid\":true,\"MinValid\":true,\"BaseValid\":true,\"Valid\":true},\"ARZ\":{\"Years\":3,\"Total\":9.0,\"Breakdown\":null,\"AAV\":3.0,\"Y1\":3.0,\"Y2\":3.0,\"Y3\":3.0,\"Y4\":3.0,\"Y5\":3.0,\"Max\":3.0,\"Min\":3.0,\"MaxValid\":true,\"MinValid\":true,\"BaseValid\":true,\"Valid\":true},\"NYM\":{\"Years\":2,\"Total\":8.0,\"Breakdown\":\"3.2,4.8\",\"AAV\":4.0,\"Y1\":3.2,\"Y2\":4.0,\"Y3\":4.0,\"Y4\":4.0,\"Y5\":4.0,\"Max\":4.0,\"Min\":3.2,\"MaxValid\":true,\"MinValid\":false,\"BaseValid\":true,\"Valid\":false},\"OAK\":{\"Years\":4,\"Total\":14.8,\"Breakdown\":null,\"AAV\":3.7,\"Y1\":3.7,\"Y2\":3.7,\"Y3\":3.7,\"Y4\":3.7,\"Y5\":3.7,\"Max\":3.7,\"Min\":3.7,\"MaxValid\":true,\"MinValid\":true,\"BaseValid\":true,\"Valid\":true},\"PHI\":{\"Years\":2,\"Total\":11.0,\"Breakdown\":null,\"AAV\":5.5,\"Y1\":5.5,\"Y2\":5.5,\"Y3\":5.5,\"Y4\":5.5,\"Y5\":5.5,\"Max\":5.5,\"Min\":5.5,\"MaxValid\":true,\"MinValid\":true,\"BaseValid\":true,\"Valid\":true},\"SD\":{\"Years\":2,\"Total\":4.97,\"Breakdown\":null,\"AAV\":2.485,\"Y1\":2.485,\"Y2\":2.485,\"Y3\":2.485,\"Y4\":2.485,\"Y5\":2.485,\"Max\":2.485,\"Min\":2.485,\"MaxValid\":true,\"MinValid\":true,\"BaseValid\":true,\"Valid\":true},\"CHC\":{\"Years\":1,\"Total\":0.5,\"Breakdown\":null,\"AAV\":0.5,\"Y1\":0.5,\"Y2\":0.5,\"Y3\":0.5,\"Y4\":0.5,\"Y5\":0.5,\"Max\":0.5,\"Min\":0.5,\"MaxValid\":true,\"MinValid\":true,\"BaseValid\":true,\"Valid\":true},\"TB\":{\"Years\":3,\"Total\":11.85,\"Breakdown\":null,\"AAV\":3.95,\"Y1\":3.95,\"Y2\":3.95,\"Y3\":3.95,\"Y4\":3.95,\"Y5\":3.95,\"Max\":3.95,\"Min\":3.95,\"MaxValid\":true,\"MinValid\":true,\"BaseValid\":true,\"Valid\":true},\"ATL\":{\"Years\":1,\"Total\":0.4,\"Breakdown\":null,\"AAV\":0.4,\"Y1\":0.4,\"Y2\":0.4,\"Y3\":0.4,\"Y4\":0.4,\"Y5\":0.4,\"Max\":0.4,\"Min\":0.4,\"MaxValid\":true,\"MinValid\":true,\"BaseValid\":false,\"Valid\":false},\"CLE\":{\"Years\":2,\"Total\":6.4,\"Breakdown\":null,\"AAV\":3.2,\"Y1\":3.2,\"Y2\":3.2,\"Y3\":3.2,\"Y4\":3.2,\"Y5\":3.2,\"Max\":3.2,\"Min\":3.2,\"MaxValid\":true,\"MinValid\":true,\"BaseValid\":true,\"Valid\":true}}", "Madison Bumgarner, SP SF": "{\"LAD\":{\"Years\":1,\"Total\":4.4,\"Breakdown\":null,\"AAV\":4.4,\"Y1\":4.4,\"Y2\":4.4,\"Y3\":4.4,\"Y4\":4.4,\"Y5\":4.4,\"Max\":4.4,\"Min\":4.4,\"MaxValid\":true,\"MinValid\":true,\"BaseValid\":true,\"Valid\":true},\"DET\":{\"Years\":1,\"Total\":5.0,\"Breakdown\":null,\"AAV\":5.0,\"Y1\":5.0,\"Y2\":5.0,\"Y3\":5.0,\"Y4\":5.0,\"Y5\":5.0,\"Max\":5.0,\"Min\":5.0,\"MaxValid\":true,\"MinValid\":true,\"BaseValid\":true,\"Valid\":true},\"ARZ\":{\"Years\":2,\"Total\":7.0,\"Breakdown\":null,\"AAV\":3.5,\"Y1\":3.5,\"Y2\":3.5,\"Y3\":3.5,\"Y4\":3.5,\"Y5\":3.5,\"Max\":3.5,\"Min\":3.5,\"MaxValid\":true,\"MinValid\":true,\"BaseValid\":true,\"Valid\":true},\"OAK\":{\"Years\":2,\"Total\":8.0,\"Breakdown\":null,\"AAV\":4.0,\"Y1\":4.0,\"Y2\":4.0,\"Y3\":4.0,\"Y4\":4.0,\"Y5\":4.0,\"Max\":4.0,\"Min\":4.0,\"MaxValid\":true,\"MinValid\":true,\"BaseValid\":true,\"Valid\":true},\"PHI\":{\"Years\":2,\"Total\":11.0,\"Breakdown\":null,\"AAV\":5.5,\"Y1\":5.5,\"Y2\":5.5,\"Y3\":5.5,\"Y4\":5.5,\"Y5\":5.5,\"Max\":5.5,\"Min\":5.5,\"MaxValid\":true,\"MinValid\":true,\"BaseValid\":true,\"Valid\":true},\"SD\":{\"Years\":2,\"Total\":3.77,\"Breakdown\":null,\"AAV\":1.885,\"Y1\":1.885,\"Y2\":1.885,\"Y3\":1.885,\"Y4\":1.885,\"Y5\":1.885,\"Max\":1.885,\"Min\":1.885,\"MaxValid\":true,\"MinValid\":true,\"BaseValid\":true,\"Valid\":true},\"TB\":{\"Years\":2,\"Total\":15.0,\"Breakdown\":null,\"AAV\":7.5,\"Y1\":7.5,\"Y2\":7.5,\"Y3\":7.5,\"Y4\":7.5,\"Y5\":7.5,\"Max\":7.5,\"Min\":7.5,\"MaxValid\":true,\"MinValid\":true,\"BaseValid\":true,\"Valid\":true},\"BOS\":{\"Years\":3,\"Total\":14.67,\"Breakdown\":null,\"AAV\":4.89,\"Y1\":4.89,\"Y2\":4.89,\"Y3\":4.89,\"Y4\":4.89,\"Y5\":4.89,\"Max\":4.89,\"Min\":4.89,\"MaxValid\":true,\"MinValid\":true,\"BaseValid\":true,\"Valid\":true},\"ATL\":{\"Years\":1,\"Total\":3.0,\"Breakdown\":null,\"AAV\":3.0,\"Y1\":3.0,\"Y2\":3.0,\"Y3\":3.0,\"Y4\":3.0,\"Y5\":3.0,\"Max\":3.0,\"Min\":3.0,\"MaxValid\":true,\"MinValid\":true,\"BaseValid\":true,\"Valid\":true},\"BAL\":{\"Years\":1,\"Total\":8.0,\"Breakdown\":null,\"AAV\":8.0,\"Y1\":8.0,\"Y2\":8.0,\"Y3\":8.0,\"Y4\":8.0,\"Y5\":8.0,\"Max\":8.0,\"Min\":8.0,\"MaxValid\":true,\"MinValid\":true,\"BaseValid\":true,\"Valid\":true},\"CLE\":{\"Years\":2,\"Total\":7.8,\"Breakdown\":null,\"AAV\":3.9,\"Y1\":3.9,\"Y2\":3.9,\"Y3\":3.9,\"Y4\":3.9,\"Y5\":3.9,\"Max\":3.9,\"Min\":3.9,\"MaxValid\":true,\"MinValid\":true,\"BaseValid\":true,\"Valid\":true},\"TOR\":{\"Years\":3,\"Total\":14.7,\"Breakdown\":null,\"AAV\":4.9,\"Y1\":4.9,\"Y2\":4.9,\"Y3\":4.9,\"Y4\":4.9,\"Y5\":4.9,\"Max\":4.9,\"Min\":4.9,\"MaxValid\":true,\"MinValid\":true,\"BaseValid\":true,\"Valid\":true}}", "Merrill Kelly, SP ARZ": "{\"NYM\":{\"Years\":1,\"Total\":1.75,\"Breakdown\":null,\"AAV\":1.75,\"Y1\":1.75,\"Y2\":1.75,\"Y3\":1.75,\"Y4\":1.75,\"Y5\":1.75,\"Max\":1.75,\"Min\":1.75,\"MaxValid\":true,\"MinValid\":true,\"BaseValid\":true,\"Valid\":true},\"BOS\":{\"Years\":2,\"Total\":3.78,\"Breakdown\":null,\"AAV\":1.89,\"Y1\":1.89,\"Y2\":1.89,\"Y3\":1.89,\"Y4\":1.89,\"Y5\":1.89,\"Max\":1.89,\"Min\":1.89,\"MaxValid\":true,\"MinValid\":true,\"BaseValid\":true,\"Valid\":true},\"CHC\":{\"Years\":4,\"Total\":1.68,\"Breakdown\":null,\"AAV\":0.42,\"Y1\":0.42,\"Y2\":0.42,\"Y3\":0.42,\"Y4\":0.42,\"Y5\":0.42,\"Max\":0.42,\"Min\":0.42,\"MaxValid\":true,\"MinValid\":true,\"BaseValid\":true,\"Valid\":true},\"TB\":{\"Years\":4,\"Total\":7.4,\"Breakdown\":null,\"AAV\":1.85,\"Y1\":1.85,\"Y2\":1.85,\"Y3\":1.85,\"Y4\":1.85,\"Y5\":1.85,\"Max\":1.85,\"Min\":1.85,\"MaxValid\":true,\"MinValid\":true,\"BaseValid\":true,\"Valid\":true},\"ATL\":{\"Years\":1,\"Total\":1.1,\"Breakdown\":null,\"AAV\":1.1,\"Y1\":1.1,\"Y2\":1.1,\"Y3\":1.1,\"Y4\":1.1,\"Y5\":1.1,\"Max\":1.1,\"Min\":1.1,\"MaxValid\":true,\"MinValid\":true,\"BaseValid\":true,\"Valid\":true}}", "Rich Hill, SP LAD": "{\"LAD\":{\"Years\":1,\"Total\":1.2,\"Breakdown\":null,\"AAV\":1.2,\"Y1\":1.2,\"Y2\":1.2,\"Y3\":1.2,\"Y4\":1.2,\"Y5\":1.2,\"Max\":1.2,\"Min\":1.2,\"MaxValid\":true,\"MinValid\":true,\"BaseValid\":true,\"Valid\":true},\"BOS\":{\"Years\":1,\"Total\":3.7,\"Breakdown\":null,\"AAV\":3.7,\"Y1\":3.7,\"Y2\":3.7,\"Y3\":3.7,\"Y4\":3.7,\"Y5\":3.7,\"Max\":3.7,\"Min\":3.7,\"MaxValid\":true,\"MinValid\":true,\"BaseValid\":true,\"Valid\":true},\"DET\":{\"Years\":1,\"Total\":0.5,\"Breakdown\":null,\"AAV\":0.5,\"Y1\":0.5,\"Y2\":0.5,\"Y3\":0.5,\"Y4\":0.5,\"Y5\":0.5,\"Max\":0.5,\"Min\":0.5,\"MaxValid\":true,\"MinValid\":true,\"BaseValid\":true,\"Valid\":true},\"ARZ\":{\"Years\":1,\"Total\":3.5,\"Breakdown\":null,\"AAV\":3.5,\"Y1\":3.5,\"Y2\":3.5,\"Y3\":3.5,\"Y4\":3.5,\"Y5\":3.5,\"Max\":3.5,\"Min\":3.5,\"MaxValid\":true,\"MinValid\":true,\"BaseValid\":true,\"Valid\":true},\"NYM\":{\"Years\":1,\"Total\":2.5,\"Breakdown\":null,\"AAV\":2.5,\"Y1\":2.5,\"Y2\":2.5,\"Y3\":2.5,\"Y4\":2.5,\"Y5\":2.5,\"Max\":2.5,\"Min\":2.5,\"MaxValid\":true,\"MinValid\":true,\"BaseValid\":true,\"Valid\":true},\"OAK\":{\"Years\":1,\"Total\":4.2,\"Breakdown\":null,\"AAV\":4.2,\"Y1\":4.2,\"Y2\":4.2,\"Y3\":4.2,\"Y4\":4.2,\"Y5\":4.2,\"Max\":4.2,\"Min\":4.2,\"MaxValid\":true,\"MinValid\":true,\"BaseValid\":true,\"Valid\":true},\"PHI\":{\"Years\":2,\"Total\":11.0,\"Breakdown\":null,\"AAV\":5.5,\"Y1\":5.5,\"Y2\":5.5,\"Y3\":5.5,\"Y4\":5.5,\"Y5\":5.5,\"Max\":5.5,\"Min\":5.5,\"MaxValid\":true,\"MinValid\":true,\"BaseValid\":true,\"Valid\":true},\"CHC\":{\"Years\":1,\"Total\":0.9,\"Breakdown\":null,\"AAV\":0.9,\"Y1\":0.9,\"Y2\":0.9,\"Y3\":0.9,\"Y4\":0.9,\"Y5\":0.9,\"Max\":0.9,\"Min\":0.9,\"MaxValid\":true,\"MinValid\":true,\"BaseValid\":true,\"Valid\":true},\"TB\":{\"Years\":1,\"Total\":5.13,\"Breakdown\":null,\"AAV\":5.13,\"Y1\":5.13,\"Y2\":5.13,\"Y3\":5.13,\"Y4\":5.13,\"Y5\":5.13,\"Max\":5.13,\"Min\":5.13,\"MaxValid\":true,\"MinValid\":true,\"BaseValid\":true,\"Valid\":true},\"ATL\":{\"Years\":1,\"Total\":2.7,\"Breakdown\":null,\"AAV\":2.7,\"Y1\":2.7,\"Y2\":2.7,\"Y3\":2.7,\"Y4\":2.7,\"Y5\":2.7,\"Max\":2.7,\"Min\":2.7,\"MaxValid\":true,\"MinValid\":true,\"BaseValid\":true,\"Valid\":true},\"CLE\":{\"Years\":1,\"Total\":4.2,\"Breakdown\":null,\"AAV\":4.2,\"Y1\":4.2,\"Y2\":4.2,\"Y3\":4.2,\"Y4\":4.2,\"Y5\":4.2,\"Max\":4.2,\"Min\":4.2,\"MaxValid\":true,\"MinValid\":true,\"BaseValid\":true,\"Valid\":true},\"TOR\":{\"Years\":1,\"Total\":4.4,\"Breakdown\":null,\"AAV\":4.4,\"Y1\":4.4,\"Y2\":4.4,\"Y3\":4.4,\"Y4\":4.4,\"Y5\":4.4,\"Max\":4.4,\"Min\":4.4,\"MaxValid\":true,\"MinValid\":true,\"BaseValid\":true,\"Valid\":true}}", "Robbie Erlin, SP SD": "{\"LAD\":{\"Years\":3,\"Total\":2.1,\"Breakdown\":null,\"AAV\":0.7,\"Y1\":0.7,\"Y2\":0.7,\"Y3\":0.7,\"Y4\":0.7,\"Y5\":0.7,\"Max\":0.7,\"Min\":0.7,\"MaxValid\":true,\"MinValid\":true,\"BaseValid\":true,\"Valid\":true},\"NYM\":{\"Years\":1,\"Total\":0.4,\"Breakdown\":null,\"AAV\":0.4,\"Y1\":0.4,\"Y2\":0.4,\"Y3\":0.4,\"Y4\":0.4,\"Y5\":0.4,\"Max\":0.4,\"Min\":0.4,\"MaxValid\":true,\"MinValid\":true,\"BaseValid\":false,\"Valid\":false},\"ATL\":{\"Years\":1,\"Total\":0.4,\"Breakdown\":null,\"AAV\":0.4,\"Y1\":0.4,\"Y2\":0.4,\"Y3\":0.4,\"Y4\":0.4,\"Y5\":0.4,\"Max\":0.4,\"Min\":0.4,\"MaxValid\":true,\"MinValid\":true,\"BaseValid\":false,\"Valid\":false},\"TOR\":{\"Years\":3,\"Total\":7.8,\"Breakdown\":null,\"AAV\":2.6,\"Y1\":2.6,\"Y2\":2.6,\"Y3\":2.6,\"Y4\":2.6,\"Y5\":2.6,\"Max\":2.6,\"Min\":2.6,\"MaxValid\":true,\"MinValid\":true,\"BaseValid\":true,\"Valid\":true}}", "Ty Blach, SP SF": "{\"CHC\":{\"Years\":1,\"Total\":0.4,\"Breakdown\":null,\"AAV\":0.4,\"Y1\":0.4,\"Y2\":0.4,\"Y3\":0.4,\"Y4\":0.4,\"Y5\":0.4,\"Max\":0.4,\"Min\":0.4,\"MaxValid\":true,\"MinValid\":true,\"BaseValid\":false,\"Valid\":false}}", "Zack Greinke, SP ARZ": "{\"LAD\":{\"Years\":1,\"Total\":4.6,\"Breakdown\":null,\"AAV\":4.6,\"Y1\":4.6,\"Y2\":4.6,\"Y3\":4.6,\"Y4\":4.6,\"Y5\":4.6,\"Max\":4.6,\"Min\":4.6,\"MaxValid\":true,\"MinValid\":true,\"BaseValid\":true,\"Valid\":true},\"DET\":{\"Years\":1,\"Total\":5.0,\"Breakdown\":null,\"AAV\":5.0,\"Y1\":5.0,\"Y2\":5.0,\"Y3\":5.0,\"Y4\":5.0,\"Y5\":5.0,\"Max\":5.0,\"Min\":5.0,\"MaxValid\":true,\"MinValid\":true,\"BaseValid\":true,\"Valid\":true},\"ARZ\":{\"Years\":1,\"Total\":4.5,\"Breakdown\":null,\"AAV\":4.5,\"Y1\":4.5,\"Y2\":4.5,\"Y3\":4.5,\"Y4\":4.5,\"Y5\":4.5,\"Max\":4.5,\"Min\":4.5,\"MaxValid\":true,\"MinValid\":true,\"BaseValid\":true,\"Valid\":true},\"OAK\":{\"Years\":2,\"Total\":10.8,\"Breakdown\":null,\"AAV\":5.4,\"Y1\":5.4,\"Y2\":5.4,\"Y3\":5.4,\"Y4\":5.4,\"Y5\":5.4,\"Max\":5.4,\"Min\":5.4,\"MaxValid\":true,\"MinValid\":true,\"BaseValid\":true,\"Valid\":true},\"PHI\":{\"Years\":1,\"Total\":7.2,\"Breakdown\":null,\"AAV\":7.2,\"Y1\":7.2,\"Y2\":7.2,\"Y3\":7.2,\"Y4\":7.2,\"Y5\":7.2,\"Max\":7.2,\"Min\":7.2,\"MaxValid\":true,\"MinValid\":true,\"BaseValid\":true,\"Valid\":true},\"BOS\":{\"Years\":2,\"Total\":14.02,\"Breakdown\":\"5.82,8.2\",\"AAV\":7.01,\"Y1\":5.82,\"Y2\":7.01,\"Y3\":7.01,\"Y4\":7.01,\"Y5\":7.01,\"Max\":7.01,\"Min\":5.82,\"MaxValid\":true,\"MinValid\":true,\"BaseValid\":true,\"Valid\":true},\"WAS\":{\"Years\":2,\"Total\":14.0,\"Breakdown\":null,\"AAV\":7.0,\"Y1\":7.0,\"Y2\":7.0,\"Y3\":7.0,\"Y4\":7.0,\"Y5\":7.0,\"Max\":7.0,\"Min\":7.0,\"MaxValid\":true,\"MinValid\":true,\"BaseValid\":true,\"Valid\":true},\"SD\":{\"Years\":2,\"Total\":5.77,\"Breakdown\":null,\"AAV\":2.885,\"Y1\":2.885,\"Y2\":2.885,\"Y3\":2.885,\"Y4\":2.885,\"Y5\":2.885,\"Max\":2.885,\"Min\":2.885,\"MaxValid\":true,\"MinValid\":true,\"BaseValid\":true,\"Valid\":true},\"TB\":{\"Years\":1,\"Total\":5.85,\"Breakdown\":null,\"AAV\":5.85,\"Y1\":5.85,\"Y2\":5.85,\"Y3\":5.85,\"Y4\":5.85,\"Y5\":5.85,\"Max\":5.85,\"Min\":5.85,\"MaxValid\":true,\"MinValid\":true,\"BaseValid\":true,\"Valid\":true},\"ATL\":{\"Years\":1,\"Total\":3.0,\"Breakdown\":null,\"AAV\":3.0,\"Y1\":3.0,\"Y2\":3.0,\"Y3\":3.0,\"Y4\":3.0,\"Y5\":3.0,\"Max\":3.0,\"Min\":3.0,\"MaxValid\":true,\"MinValid\":true,\"BaseValid\":true,\"Valid\":true},\"BAL\":{\"Years\":1,\"Total\":9.0,\"Breakdown\":null,\"AAV\":9.0,\"Y1\":9.0,\"Y2\":9.0,\"Y3\":9.0,\"Y4\":9.0,\"Y5\":9.0,\"Max\":9.0,\"Min\":9.0,\"MaxValid\":true,\"MinValid\":true,\"BaseValid\":true,\"Valid\":true},\"CLE\":{\"Years\":2,\"Total\":11.8,\"Breakdown\":null,\"AAV\":5.9,\"Y1\":5.9,\"Y2\":5.9,\"Y3\":5.9,\"Y4\":5.9,\"Y5\":5.9,\"Max\":5.9,\"Min\":5.9,\"MaxValid\":true,\"MinValid\":true,\"BaseValid\":true,\"Valid\":true},\"TOR\":{\"Years\":1,\"Total\":8.9,\"Breakdown\":null,\"AAV\":8.9,\"Y1\":8.9,\"Y2\":8.9,\"Y3\":8.9,\"Y4\":8.9,\"Y5\":8.9,\"Max\":8.9,\"Min\":8.9,\"MaxValid\":true,\"MinValid\":true,\"BaseValid\":true,\"Valid\":true}}", "Chad Bettis, RP COL": "{\"CHC\":{\"Years\":1,\"Total\":0.4,\"Breakdown\":null,\"AAV\":0.4,\"Y1\":0.4,\"Y2\":0.4,\"Y3\":0.4,\"Y4\":0.4,\"Y5\":0.4,\"Max\":0.4,\"Min\":0.4,\"MaxValid\":true,\"MinValid\":true,\"BaseValid\":false,\"Valid\":false}}", "Chris Stratton, RP SF": "{\"CHC\":{\"Years\":1,\"Total\":0.4,\"Breakdown\":null,\"AAV\":0.4,\"Y1\":0.4,\"Y2\":0.4,\"Y3\":0.4,\"Y4\":0.4,\"Y5\":0.4,\"Max\":0.4,\"Min\":0.4,\"MaxValid\":true,\"MinValid\":true,\"BaseValid\":false,\"Valid\":false}}", "Craig Stammen, RP SD": "{\"BOS\":{\"Years\":2,\"Total\":1.58,\"Breakdown\":null,\"AAV\":0.79,\"Y1\":0.79,\"Y2\":0.79,\"Y3\":0.79,\"Y4\":0.79,\"Y5\":0.79,\"Max\":0.79,\"Min\":0.79,\"MaxValid\":true,\"MinValid\":true,\"BaseValid\":true,\"Valid\":true},\"NYM\":{\"Years\":1,\"Total\":0.4,\"Breakdown\":null,\"AAV\":0.4,\"Y1\":0.4,\"Y2\":0.4,\"Y3\":0.4,\"Y4\":0.4,\"Y5\":0.4,\"Max\":0.4,\"Min\":0.4,\"MaxValid\":true,\"MinValid\":true,\"BaseValid\":false,\"Valid\":false},\"OAK\":{\"Years\":1,\"Total\":0.8,\"Breakdown\":null,\"AAV\":0.8,\"Y1\":0.8,\"Y2\":0.8,\"Y3\":0.8,\"Y4\":0.8,\"Y5\":0.8,\"Max\":0.8,\"Min\":0.8,\"MaxValid\":true,\"MinValid\":true,\"BaseValid\":true,\"Valid\":true},\"PHI\":{\"Years\":1,\"Total\":0.65,\"Breakdown\":null,\"AAV\":0.65,\"Y1\":0.65,\"Y2\":0.65,\"Y3\":0.65,\"Y4\":0.65,\"Y5\":0.65,\"Max\":0.65,\"Min\":0.65,\"MaxValid\":true,\"MinValid\":true,\"BaseValid\":true,\"Valid\":true},\"WAS\":{\"Years\":1,\"Total\":1.0,\"Breakdown\":null,\"AAV\":1.0,\"Y1\":1.0,\"Y2\":1.0,\"Y3\":1.0,\"Y4\":1.0,\"Y5\":1.0,\"Max\":1.0,\"Min\":1.0,\"MaxValid\":true,\"MinValid\":true,\"BaseValid\":true,\"Valid\":true},\"CLE\":{\"Years\":1,\"Total\":1.3,\"Breakdown\":null,\"AAV\":1.3,\"Y1\":1.3,\"Y2\":1.3,\"Y3\":1.3,\"Y4\":1.3,\"Y5\":1.3,\"Max\":1.3,\"Min\":1.3,\"MaxValid\":true,\"MinValid\":true,\"BaseValid\":true,\"Valid\":true},\"TOR\":{\"Years\":1,\"Total\":0.9,\"Breakdown\":null,\"AAV\":0.9,\"Y1\":0.9,\"Y2\":0.9,\"Y3\":0.9,\"Y4\":0.9,\"Y5\":0.9,\"Max\":0.9,\"Min\":0.9,\"MaxValid\":true,\"MinValid\":true,\"BaseValid\":true,\"Valid\":true}}", "Greg Holland, RP ARZ": "{\"BOS\":{\"Years\":2,\"Total\":0.8,\"Breakdown\":null,\"AAV\":0.4,\"Y1\":0.4,\"Y2\":0.4,\"Y3\":0.4,\"Y4\":0.4,\"Y5\":0.4,\"Max\":0.4,\"Min\":0.4,\"MaxValid\":true,\"MinValid\":true,\"BaseValid\":false,\"Valid\":false},\"NYM\":{\"Years\":1,\"Total\":0.85,\"Breakdown\":null,\"AAV\":0.85,\"Y1\":0.85,\"Y2\":0.85,\"Y3\":0.85,\"Y4\":0.85,\"Y5\":0.85,\"Max\":0.85,\"Min\":0.85,\"MaxValid\":true,\"MinValid\":true,\"BaseValid\":true,\"Valid\":true},\"PHI\":{\"Years\":1,\"Total\":0.65,\"Breakdown\":null,\"AAV\":0.65,\"Y1\":0.65,\"Y2\":0.65,\"Y3\":0.65,\"Y4\":0.65,\"Y5\":0.65,\"Max\":0.65,\"Min\":0.65,\"MaxValid\":true,\"MinValid\":true,\"BaseValid\":true,\"Valid\":true},\"TB\":{\"Years\":1,\"Total\":2.97,\"Breakdown\":null,\"AAV\":2.97,\"Y1\":2.97,\"Y2\":2.97,\"Y3\":2.97,\"Y4\":2.97,\"Y5\":2.97,\"Max\":2.97,\"Min\":2.97,\"MaxValid\":true,\"MinValid\":true,\"BaseValid\":true,\"Valid\":true},\"ATL\":{\"Years\":1,\"Total\":0.45,\"Breakdown\":null,\"AAV\":0.45,\"Y1\":0.45,\"Y2\":0.45,\"Y3\":0.45,\"Y4\":0.45,\"Y5\":0.45,\"Max\":0.45,\"Min\":0.45,\"MaxValid\":true,\"MinValid\":true,\"BaseValid\":true,\"Valid\":true},\"CLE\":{\"Years\":1,\"Total\":0.4,\"Breakdown\":null,\"AAV\":0.4,\"Y1\":0.4,\"Y2\":0.4,\"Y3\":0.4,\"Y4\":0.4,\"Y5\":0.4,\"Max\":0.4,\"Min\":0.4,\"MaxValid\":true,\"MinValid\":true,\"BaseValid\":false,\"Valid\":false},\"TOR\":{\"Years\":2,\"Total\":1.8,\"Breakdown\":null,\"AAV\":0.9,\"Y1\":0.9,\"Y2\":0.9,\"Y3\":0.9,\"Y4\":0.9,\"Y5\":0.9,\"Max\":0.9,\"Min\":0.9,\"MaxValid\":true,\"MinValid\":true,\"BaseValid\":true,\"Valid\":true}}", "Jake McGee, RP COL": "{\"NYM\":{\"Years\":1,\"Total\":0.65,\"Breakdown\":null,\"AAV\":0.65,\"Y1\":0.65,\"Y2\":0.65,\"Y3\":0.65,\"Y4\":0.65,\"Y5\":0.65,\"Max\":0.65,\"Min\":0.65,\"MaxValid\":true,\"MinValid\":true,\"BaseValid\":true,\"Valid\":true}}", "Luis Perdomo, RP SD": "{\"CHC\":{\"Years\":1,\"Total\":0.4,\"Breakdown\":null,\"AAV\":0.4,\"Y1\":0.4,\"Y2\":0.4,\"Y3\":0.4,\"Y4\":0.4,\"Y5\":0.4,\"Max\":0.4,\"Min\":0.4,\"MaxValid\":true,\"MinValid\":true,\"BaseValid\":false,\"Valid\":false}}", "Mark Melancon, RP SF": "{\"BOS\":{\"Years\":1,\"Total\":0.4,\"Breakdown\":null,\"AAV\":0.4,\"Y1\":0.4,\"Y2\":0.4,\"Y3\":0.4,\"Y4\":0.4,\"Y5\":0.4,\"Max\":0.4,\"Min\":0.4,\"MaxValid\":true,\"MinValid\":true,\"BaseValid\":false,\"Valid\":false},\"NYM\":{\"Years\":1,\"Total\":2.75,\"Breakdown\":null,\"AAV\":2.75,\"Y1\":2.75,\"Y2\":2.75,\"Y3\":2.75,\"Y4\":2.75,\"Y5\":2.75,\"Max\":2.75,\"Min\":2.75,\"MaxValid\":true,\"MinValid\":true,\"BaseValid\":true,\"Valid\":true}}", "Pedro Baez, RP LAD": "{\"BAL\":{\"Years\":1,\"Total\":1.0,\"Breakdown\":null,\"AAV\":1.0,\"Y1\":1.0,\"Y2\":1.0,\"Y3\":1.0,\"Y4\":1.0,\"Y5\":1.0,\"Max\":1.0,\"Min\":1.0,\"MaxValid\":true,\"MinValid\":true,\"BaseValid\":true,\"Valid\":true},\"CLE\":{\"Years\":1,\"Total\":0.4,\"Breakdown\":null,\"AAV\":0.4,\"Y1\":0.4,\"Y2\":0.4,\"Y3\":0.4,\"Y4\":0.4,\"Y5\":0.4,\"Max\":0.4,\"Min\":0.4,\"MaxValid\":true,\"MinValid\":true,\"BaseValid\":false,\"Valid\":false}}", "Scott Alexander, RP LAD": "{\"CLE\":{\"Years\":1,\"Total\":0.4,\"Breakdown\":null,\"AAV\":0.4,\"Y1\":0.4,\"Y2\":0.4,\"Y3\":0.4,\"Y4\":0.4,\"Y5\":0.4,\"Max\":0.4,\"Min\":0.4,\"MaxValid\":true,\"MinValid\":true,\"BaseValid\":false,\"Valid\":false}}", "Seung-Hwan Oh, RP COL": "{\"BOS\":{\"Years\":1,\"Total\":0.41,\"Breakdown\":null,\"AAV\":0.41,\"Y1\":0.41,\"Y2\":0.41,\"Y3\":0.41,\"Y4\":0.41,\"Y5\":0.41,\"Max\":0.41,\"Min\":0.41,\"MaxValid\":true,\"MinValid\":true,\"BaseValid\":true,\"Valid\":true},\"OAK\":{\"Years\":1,\"Total\":0.55,\"Breakdown\":null,\"AAV\":0.55,\"Y1\":0.55,\"Y2\":0.55,\"Y3\":0.55,\"Y4\":0.55,\"Y5\":0.55,\"Max\":0.55,\"Min\":0.55,\"MaxValid\":true,\"MinValid\":true,\"BaseValid\":true,\"Valid\":true},\"CLE\":{\"Years\":1,\"Total\":0.4,\"Breakdown\":null,\"AAV\":0.4,\"Y1\":0.4,\"Y2\":0.4,\"Y3\":0.4,\"Y4\":0.4,\"Y5\":0.4,\"Max\":0.4,\"Min\":0.4,\"MaxValid\":true,\"MinValid\":true,\"BaseValid\":false,\"Valid\":false}}", "Tony Cingrani, RP LAD": "{\"TOR\":{\"Years\":3,\"Total\":2.7,\"Breakdown\":null,\"AAV\":0.9,\"Y1\":0.9,\"Y2\":0.9,\"Y3\":0.9,\"Y4\":0.9,\"Y5\":0.9,\"Max\":0.9,\"Min\":0.9,\"MaxValid\":true,\"MinValid\":true,\"BaseValid\":true,\"Valid\":true}}", "Tony Watson, RP SF": "{\"BOS\":{\"Years\":1,\"Total\":0.41,\"Breakdown\":null,\"AAV\":0.41,\"Y1\":0.41,\"Y2\":0.41,\"Y3\":0.41,\"Y4\":0.41,\"Y5\":0.41,\"Max\":0.41,\"Min\":0.41,\"MaxValid\":true,\"MinValid\":true,\"BaseValid\":true,\"Valid\":true},\"OAK\":{\"Years\":1,\"Total\":0.9,\"Breakdown\":null,\"AAV\":0.9,\"Y1\":0.9,\"Y2\":0.9,\"Y3\":0.9,\"Y4\":0.9,\"Y5\":0.9,\"Max\":0.9,\"Min\":0.9,\"MaxValid\":true,\"MinValid\":true,\"BaseValid\":true,\"Valid\":true},\"PHI\":{\"Years\":1,\"Total\":0.65,\"Breakdown\":null,\"AAV\":0.65,\"Y1\":0.65,\"Y2\":0.65,\"Y3\":0.65,\"Y4\":0.65,\"Y5\":0.65,\"Max\":0.65,\"Min\":0.65,\"MaxValid\":true,\"MinValid\":true,\"BaseValid\":true,\"Valid\":true},\"WAS\":{\"Years\":2,\"Total\":2.0,\"Breakdown\":null,\"AAV\":1.0,\"Y1\":1.0,\"Y2\":1.0,\"Y3\":1.0,\"Y4\":1.0,\"Y5\":1.0,\"Max\":1.0,\"Min\":1.0,\"MaxValid\":true,\"MinValid\":true,\"BaseValid\":true,\"Valid\":true},\"BAL\":{\"Years\":1,\"Total\":1.0,\"Breakdown\":null,\"AAV\":1.0,\"Y1\":1.0,\"Y2\":1.0,\"Y3\":1.0,\"Y4\":1.0,\"Y5\":1.0,\"Max\":1.0,\"Min\":1.0,\"MaxValid\":true,\"MinValid\":true,\"BaseValid\":true,\"Valid\":true},\"CLE\":{\"Years\":1,\"Total\":0.8,\"Breakdown\":null,\"AAV\":0.8,\"Y1\":0.8,\"Y2\":0.8,\"Y3\":0.8,\"Y4\":0.8,\"Y5\":0.8,\"Max\":0.8,\"Min\":0.8,\"MaxValid\":true,\"MinValid\":true,\"BaseValid\":true,\"Valid\":true},\"TOR\":{\"Years\":2,\"Total\":4.6,\"Breakdown\":null,\"AAV\":2.3,\"Y1\":2.3,\"Y2\":2.3,\"Y3\":2.3,\"Y4\":2.3,\"Y5\":2.3,\"Max\":2.3,\"Min\":2.3,\"MaxValid\":true,\"MinValid\":true,\"BaseValid\":true,\"Valid\":true}}", "Trey Wingenter, RP SD": "{\"PIT\":{\"Years\":4,\"Total\":3.12,\"Breakdown\":null,\"AAV\":0.78,\"Y1\":0.78,\"Y2\":0.78,\"Y3\":0.78,\"Y4\":0.78,\"Y5\":0.78,\"Max\":0.78,\"Min\":0.78,\"MaxValid\":true,\"MinValid\":true,\"BaseValid\":true,\"Valid\":true}}", "Wade Davis, RP COL": "{\"BOS\":{\"Years\":1,\"Total\":4.19,\"Breakdown\":null,\"AAV\":4.19,\"Y1\":4.19,\"Y2\":4.19,\"Y3\":4.19,\"Y4\":4.19,\"Y5\":4.19,\"Max\":4.19,\"Min\":4.19,\"MaxValid\":true,\"MinValid\":true,\"BaseValid\":true,\"Valid\":true},\"ARZ\":{\"Years\":1,\"Total\":5.6,\"Breakdown\":null,\"AAV\":5.6,\"Y1\":5.6,\"Y2\":5.6,\"Y3\":5.6,\"Y4\":5.6,\"Y5\":5.6,\"Max\":5.6,\"Min\":5.6,\"MaxValid\":true,\"MinValid\":true,\"BaseValid\":true,\"Valid\":true},\"OAK\":{\"Years\":2,\"Total\":6.0,\"Breakdown\":null,\"AAV\":3.0,\"Y1\":3.0,\"Y2\":3.0,\"Y3\":3.0,\"Y4\":3.0,\"Y5\":3.0,\"Max\":3.0,\"Min\":3.0,\"MaxValid\":true,\"MinValid\":true,\"BaseValid\":true,\"Valid\":true},\"KC\":{\"Years\":1,\"Total\":4.05,\"Breakdown\":null,\"AAV\":4.05,\"Y1\":4.05,\"Y2\":4.05,\"Y3\":4.05,\"Y4\":4.05,\"Y5\":4.05,\"Max\":4.05,\"Min\":4.05,\"MaxValid\":true,\"MinValid\":true,\"BaseValid\":true,\"Valid\":true},\"PHI\":{\"Years\":1,\"Total\":7.2,\"Breakdown\":null,\"AAV\":7.2,\"Y1\":7.2,\"Y2\":7.2,\"Y3\":7.2,\"Y4\":7.2,\"Y5\":7.2,\"Max\":7.2,\"Min\":7.2,\"MaxValid\":true,\"MinValid\":true,\"BaseValid\":true,\"Valid\":true},\"SD\":{\"Years\":1,\"Total\":2.77,\"Breakdown\":null,\"AAV\":2.77,\"Y1\":2.77,\"Y2\":2.77,\"Y3\":2.77,\"Y4\":2.77,\"Y5\":2.77,\"Max\":2.77,\"Min\":2.77,\"MaxValid\":true,\"MinValid\":true,\"BaseValid\":true,\"Valid\":true},\"TB\":{\"Years\":1,\"Total\":8.0,\"Breakdown\":null,\"AAV\":8.0,\"Y1\":8.0,\"Y2\":8.0,\"Y3\":8.0,\"Y4\":8.0,\"Y5\":8.0,\"Max\":8.0,\"Min\":8.0,\"MaxValid\":true,\"MinValid\":true,\"BaseValid\":true,\"Valid\":true},\"ATL\":{\"Years\":1,\"Total\":3.0,\"Breakdown\":null,\"AAV\":3.0,\"Y1\":3.0,\"Y2\":3.0,\"Y3\":3.0,\"Y4\":3.0,\"Y5\":3.0,\"Max\":3.0,\"Min\":3.0,\"MaxValid\":true,\"MinValid\":true,\"BaseValid\":true,\"Valid\":true},\"CLE\":{\"Years\":1,\"Total\":2.1,\"Breakdown\":null,\"AAV\":2.1,\"Y1\":2.1,\"Y2\":2.1,\"Y3\":2.1,\"Y4\":2.1,\"Y5\":2.1,\"Max\":2.1,\"Min\":2.1,\"MaxValid\":true,\"MinValid\":true,\"BaseValid\":true,\"Valid\":true},\"TOR\":{\"Years\":1,\"Total\":4.8,\"Breakdown\":null,\"AAV\":4.8,\"Y1\":4.8,\"Y2\":4.8,\"Y3\":4.8,\"Y4\":4.8,\"Y5\":4.8,\"Max\":4.8,\"Min\":4.8,\"MaxValid\":true,\"MinValid\":true,\"BaseValid\":true,\"Valid\":true}}"}